odoo/addons/sale_procurement_customer/README.rst
odoo/addons/sale_procurement_customer/__init__.py
odoo/addons/sale_procurement_customer/__manifest__.py
odoo/addons/sale_procurement_customer/i18n/fr.po
odoo/addons/sale_procurement_customer/i18n/hr.po
odoo/addons/sale_procurement_customer/i18n/it.po
odoo/addons/sale_procurement_customer/i18n/sale_procurement_customer.pot
odoo/addons/sale_procurement_customer/models/__init__.py
odoo/addons/sale_procurement_customer/models/sale_order_line.py
odoo/addons/sale_procurement_customer/readme/CONTRIBUTORS.rst
odoo/addons/sale_procurement_customer/readme/DESCRIPTION.rst
odoo/addons/sale_procurement_customer/readme/USAGE.rst
odoo/addons/sale_procurement_customer/static/description/icon.png
odoo/addons/sale_procurement_customer/static/description/index.html
odoo/addons/sale_procurement_customer/tests/__init__.py
odoo/addons/sale_procurement_customer/tests/test_procurement_customer.py
odoo_addon_sale_procurement_customer-16.0.1.0.0.7.dist-info/METADATA
odoo_addon_sale_procurement_customer-16.0.1.0.0.7.dist-info/WHEEL
odoo_addon_sale_procurement_customer-16.0.1.0.0.7.dist-info/top_level.txt
odoo_addon_sale_procurement_customer-16.0.1.0.0.7.dist-info/RECORD
